{"data":[{"ObjectIdentifier":"S-1-5-21-1487982659-1829050783-2281216199-500","IsDeleted":false,"IsACLProtected":false,"Properties":{"domain":"PUPPY.HTB","name":"ADMINISTRATOR@PUPPY.HTB","domainsid":"S-1-5-21-1487982659-1829050783-2281216199","isaclprotected":false,"distinguishedname":"CN=ADMINISTRATOR,CN=USERS,DC=PUPPY,DC=HTB","highvalue":false,"description":"Built-in account for administering the computer/domain","whencreated":1739965512,"sensitive":true,"dontreqpreauth":false,"passwordnotreqd":false,"unconstraineddelegation":false,"pwdneverexpires":true,"enabled":true,"trustedtoauth":false,"lastlogon":1759639986,"lastlogontimestamp":1759639975,"pwdlastset":1739993608,"serviceprincipalnames":[],"hasspn":false,"displayname":"","email":"","title":"","homedirectory":"","logonscript":"","useraccountcontrol":1114624,"samaccountname":"Administrator","userpassword":"","unixpassword":"","unicodepassword":"","sfupassword":"","admincount":true,"supportedencryptiontypes":[],"sidhistory":[],"allowedtodelegate":[]},"PrimaryGroupSID":"S-1-5-21-1487982659-1829050783-2281216199-513","SPNTargets":[],"UnconstrainedDelegation":false,"DomainSID":"S-1-5-21-1487982659-1829050783-2281216199","Aces":[{"PrincipalSID":"S-1-5-21-1487982659-1829050783-2281216199-512","PrincipalType":"Group","RightName":"Owns","IsInherited":false,"InheritanceHash":""},{"PrincipalSID":"S-1-5-21-1487982659-1829050783-2281216199-512","PrincipalType":"Group","RightName":"GenericWrite","IsInherited":false,"InheritanceHash":""},{"PrincipalSID":"S-1-5-21-1487982659-1829050783-2281216199-512","PrincipalType":"Group","RightName":"WriteOwner","IsInherited":false,"InheritanceHash":""},{"PrincipalSID":"S-1-5-21-1487982659-1829050783-2281216199-512","PrincipalType":"Group","RightName":"AllExtendedRights","IsInherited":false,"InheritanceHash":""},{"PrincipalSID":"S-1-5-21-1487982659-1829050783-2281216199-512","PrincipalType":"Group","RightName":"WriteDacl","IsInherited":false,"InheritanceHash":""},{"PrincipalSID":"S-1-5-21-1487982659-1829050783-2281216199-519","PrincipalType":"Group","RightName":"GenericWrite","IsInherited":false,"InheritanceHash":""},{"PrincipalSID":"S-1-5-21-1487982659-1829050783-2281216199-519","PrincipalType":"Group","RightName":"WriteOwner","IsInherited":false,"InheritanceHash":""},{"PrincipalSID":"S-1-5-21-1487982659-1829050783-2281216199-519","PrincipalType":"Group","RightName":"AllExtendedRights","IsInherited":false,"InheritanceHash":""},{"PrincipalSID":"S-1-5-21-1487982659-1829050783-2281216199-519","PrincipalType":"Group","RightName":"WriteDacl","IsInherited":false,"InheritanceHash":""},{"PrincipalSID":"PUPPY.HTB-S-1-5-32-544","PrincipalType":"Group","RightName":"GenericWrite","IsInherited":false,"InheritanceHash":""},{"PrincipalSID":"PUPPY.HTB-S-1-5-32-544","PrincipalType":"Group","RightName":"WriteOwner","IsInherited":false,"InheritanceHash":""},{"PrincipalSID":"PUPPY.HTB-S-1-5-32-544","PrincipalType":"Group","RightName":"AllExtendedRights","IsInherited":false,"InheritanceHash":""},{"PrincipalSID":"PUPPY.HTB-S-1-5-32-544","PrincipalType":"Group","RightName":"WriteDacl","IsInherited":false,"InheritanceHash":""}],"AllowedToDelegate":[],"HasSIDHistory":[],"ContainedBy":{"ObjectIdentifier":"3F93AA72-387D-4B17-9523-1CA9CF985828","ObjectType":"Container"}},{"ObjectIdentifier":"S-1-5-21-1487982659-1829050783-2281216199-501","IsDeleted":false,"IsACLProtected":false,"Properties":{"domain":"PUPPY.HTB","name":"GUEST@PUPPY.HTB","domainsid":"S-1-5-21-1487982659-1829050783-2281216199","isaclprotected":false,"distinguishedname":"CN=GUEST,CN=USERS,DC=PUPPY,DC=HTB","highvalue":false,"description":"Built-in account for guest access to the computer/domain","whencreated":1739965512,"sensitive":false,"dontreqpreauth":false,"passwordnotreqd":true,"unconstraineddelegation":false,"pwdneverexpires":true,"enabled":false,"trustedtoauth":false,"lastlogon":0,"lastlogontimestamp":0,"pwdlastset":0,"serviceprincipalnames":[],"hasspn":false,"displayname":"","email":"","title":"","homedirectory":"","logonscript":"","useraccountcontrol":66082,"samaccountname":"Guest","userpassword":"","unixpassword":"","unicodepassword":"","sfupassword":"","admincount":false,"supportedencryptiontypes":[],"sidhistory":[],"allowedtodelegate":[]},"PrimaryGroupSID":"S-1-5-21-1487982659-1829050783-2281216199-514","SPNTargets":[],"UnconstrainedDelegation":false,"DomainSID":"S-1-5-21-1487982659-1829050783-2281216199","Aces":[{"PrincipalSID":"PUPPY.HTB-S-1-5-32-544","PrincipalType":"Group","RightName":"Owns","IsInherited":false,"InheritanceHash":""},{"PrincipalSID":"S-1-5-21-1487982659-1829050783-2281216199-512","PrincipalType":"Group","RightName":"GenericAll","IsInherited":false,"InheritanceHash":""},{"PrincipalSID":"PUPPY.HTB-S-1-5-32-548","PrincipalType":"Group","RightName":"GenericAll","IsInherited":false,"InheritanceHash":""},{"PrincipalSID":"S-1-5-21-1487982659-1829050783-2281216199-526","PrincipalType":"Group","RightName":"AddKeyCredentialLink","IsInherited":true,"InheritanceHash":""},{"PrincipalSID":"S-1-5-21-1487982659-1829050783-2281216199-527","PrincipalType":"Group","RightName":"AddKeyCredentialLink","IsInherited":true,"InheritanceHash":""},{"PrincipalSID":"S-1-5-21-1487982659-1829050783-2281216199-519","PrincipalType":"Group","RightName":"GenericAll","IsInherited":true,"InheritanceHash":""},{"PrincipalSID":"PUPPY.HTB-S-1-5-32-544","PrincipalType":"Group","RightName":"GenericWrite","IsInherited":true,"InheritanceHash":""},{"PrincipalSID":"PUPPY.HTB-S-1-5-32-544","PrincipalType":"Group","RightName":"WriteOwner","IsInherited":true,"InheritanceHash":""},{"PrincipalSID":"PUPPY.HTB-S-1-5-32-544","PrincipalType":"Group","RightName":"AllExtendedRights","IsInherited":true,"InheritanceHash":""},{"PrincipalSID":"PUPPY.HTB-S-1-5-32-544","PrincipalType":"Group","RightName":"WriteDacl","IsInherited":true,"InheritanceHash":""}],"AllowedToDelegate":[],"HasSIDHistory":[],"ContainedBy":{"ObjectIdentifier":"3F93AA72-387D-4B17-9523-1CA9CF985828","ObjectType":"Container"}},{"ObjectIdentifier":"S-1-5-21-1487982659-1829050783-2281216199-502","IsDeleted":false,"IsACLProtected":false,"Properties":{"domain":"PUPPY.HTB","name":"KRBTGT@PUPPY.HTB","domainsid":"S-1-5-21-1487982659-1829050783-2281216199","isaclprotected":false,"distinguishedname":"CN=KRBTGT,CN=USERS,DC=PUPPY,DC=HTB","highvalue":false,"description":"Key Distribution Center Service Account","whencreated":1739965575,"sensitive":false,"dontreqpreauth":false,"passwordnotreqd":false,"unconstraineddelegation":false,"pwdneverexpires":false,"enabled":false,"trustedtoauth":false,"lastlogon":0,"lastlogontimestamp":0,"pwdlastset":1739965575,"serviceprincipalnames":["kadmin/changepw"],"hasspn":true,"displayname":"","email":"","title":"","homedirectory":"","logonscript":"","useraccountcontrol":514,"samaccountname":"krbtgt","userpassword":"","unixpassword":"","unicodepassword":"","sfupassword":"","admincount":true,"supportedencryptiontypes":["Not defined"],"sidhistory":[],"allowedtodelegate":[]},"PrimaryGroupSID":"S-1-5-21-1487982659-1829050783-2281216199-513","SPNTargets":[],"UnconstrainedDelegation":false,"DomainSID":"S-1-5-21-1487982659-1829050783-2281216199","Aces":[{"PrincipalSID":"S-1-5-21-1487982659-1829050783-2281216199-512","PrincipalType":"Group","RightName":"Owns","IsInherited":false,"InheritanceHash":""},{"PrincipalSID":"S-1-5-21-1487982659-1829050783-2281216199-512","PrincipalType":"Group","RightName":"GenericWrite","IsInherited":false,"InheritanceHash":""},{"PrincipalSID":"S-1-5-21-1487982659-1829050783-2281216199-512","PrincipalType":"Group","RightName":"WriteOwner","IsInherited":false,"InheritanceHash":""},{"PrincipalSID":"S-1-5-21-1487982659-1829050783-2281216199-512","PrincipalType":"Group","RightName":"AllExtendedRights","IsInherited":false,"InheritanceHash":""},{"PrincipalSID":"S-1-5-21-1487982659-1829050783-2281216199-512","PrincipalType":"Group","RightName":"WriteDacl","IsInherited":false,"InheritanceHash":""},{"PrincipalSID":"S-1-5-21-1487982659-1829050783-2281216199-519","PrincipalType":"Group","RightName":"GenericWrite","IsInherited":false,"InheritanceHash":""},{"PrincipalSID":"S-1-5-21-1487982659-1829050783-2281216199-519","PrincipalType":"Group","RightName":"WriteOwner","IsInherited":false,"InheritanceHash":""},{"PrincipalSID":"S-1-5-21-1487982659-1829050783-2281216199-519","PrincipalType":"Group","RightName":"AllExtendedRights","IsInherited":false,"InheritanceHash":""},{"PrincipalSID":"S-1-5-21-1487982659-1829050783-2281216199-519","PrincipalType":"Group","RightName":"WriteDacl","IsInherited":false,"InheritanceHash":""},{"PrincipalSID":"PUPPY.HTB-S-1-5-32-544","PrincipalType":"Group","RightName":"GenericWrite","IsInherited":false,"InheritanceHash":""},{"PrincipalSID":"PUPPY.HTB-S-1-5-32-544","PrincipalType":"Group","RightName":"WriteOwner","IsInherited":false,"InheritanceHash":""},{"PrincipalSID":"PUPPY.HTB-S-1-5-32-544","PrincipalType":"Group","RightName":"AllExtendedRights","IsInherited":false,"InheritanceHash":""},{"PrincipalSID":"PUPPY.HTB-S-1-5-32-544","PrincipalType":"Group","RightName":"WriteDacl","IsInherited":false,"InheritanceHash":""}],"AllowedToDelegate":[],"HasSIDHistory":[],"ContainedBy":{"ObjectIdentifier":"3F93AA72-387D-4B17-9523-1CA9CF985828","ObjectType":"Container"}},{"ObjectIdentifier":"S-1-5-21-1487982659-1829050783-2281216199-1103","IsDeleted":false,"IsACLProtected":false,"Properties":{"domain":"PUPPY.HTB","name":"LEVI.JAMES@PUPPY.HTB","domainsid":"S-1-5-21-1487982659-1829050783-2281216199","isaclprotected":false,"distinguishedname":"CN=LEVI B. JAMES,OU=MANPOWER,DC=PUPPY,DC=HTB","highvalue":false,"description":null,"whencreated":1739967056,"sensitive":false,"dontreqpreauth":false,"passwordnotreqd":false,"unconstraineddelegation":false,"pwdneverexpires":true,"enabled":true,"trustedtoauth":false,"lastlogon":1759759460,"lastlogontimestamp":1759642554,"pwdlastset":1739967056,"serviceprincipalnames":[],"hasspn":false,"displayname":"Levi B. James","email":"","title":"","homedirectory":"","logonscript":"","useraccountcontrol":66048,"samaccountname":"levi.james","userpassword":"","unixpassword":"","unicodepassword":"","sfupassword":"","admincount":false,"supportedencryptiontypes":["Not defined"],"sidhistory":[],"allowedtodelegate":[]},"PrimaryGroupSID":"S-1-5-21-1487982659-1829050783-2281216199-513","SPNTargets":[],"UnconstrainedDelegation":false,"DomainSID":"S-1-5-21-1487982659-1829050783-2281216199","Aces":[{"PrincipalSID":"S-1-5-21-1487982659-1829050783-2281216199-512","PrincipalType":"Group","RightName":"Owns","IsInherited":false,"InheritanceHash":""},{"PrincipalSID":"S-1-5-21-1487982659-1829050783-2281216199-512","PrincipalType":"Group","RightName":"GenericAll","IsInherited":false,"InheritanceHash":""},{"PrincipalSID":"PUPPY.HTB-S-1-5-32-548","PrincipalType":"Group","RightName":"GenericAll","IsInherited":false,"InheritanceHash":""},{"PrincipalSID":"S-1-5-21-1487982659-1829050783-2281216199-526","PrincipalType":"Group","RightName":"AddKeyCredentialLink","IsInherited":true,"InheritanceHash":""},{"PrincipalSID":"S-1-5-21-1487982659-1829050783-2281216199-527","PrincipalType":"Group","RightName":"AddKeyCredentialLink","IsInherited":true,"InheritanceHash":""},{"PrincipalSID":"S-1-5-21-1487982659-1829050783-2281216199-519","PrincipalType":"Group","RightName":"GenericAll","IsInherited":true,"InheritanceHash":""},{"PrincipalSID":"PUPPY.HTB-S-1-5-32-544","PrincipalType":"Group","RightName":"GenericWrite","IsInherited":true,"InheritanceHash":""},{"PrincipalSID":"PUPPY.HTB-S-1-5-32-544","PrincipalType":"Group","RightName":"WriteOwner","IsInherited":true,"InheritanceHash":""},{"PrincipalSID":"PUPPY.HTB-S-1-5-32-544","PrincipalType":"Group","RightName":"AllExtendedRights","IsInherited":true,"InheritanceHash":""},{"PrincipalSID":"PUPPY.HTB-S-1-5-32-544","PrincipalType":"Group","RightName":"WriteDacl","IsInherited":true,"InheritanceHash":""}],"AllowedToDelegate":[],"HasSIDHistory":[],"ContainedBy":{"ObjectIdentifier":"6E94915D-A2E4-4EB7-8448-7728B6D528C4","ObjectType":"OU"}},{"ObjectIdentifier":"S-1-5-21-1487982659-1829050783-2281216199-1104","IsDeleted":false,"IsACLProtected":false,"Properties":{"domain":"PUPPY.HTB","name":"ANT.EDWARDS@PUPPY.HTB","domainsid":"S-1-5-21-1487982659-1829050783-2281216199","isaclprotected":false,"distinguishedname":"CN=ANTHONY J. EDWARDS,DC=PUPPY,DC=HTB","highvalue":false,"description":null,"whencreated":1739967194,"sensitive":false,"dontreqpreauth":false,"passwordnotreqd":false,"unconstraineddelegation":false,"pwdneverexpires":true,"enabled":true,"trustedtoauth":false,"lastlogon":1759754578,"lastlogontimestamp":1759654460,"pwdlastset":1739967194,"serviceprincipalnames":[],"hasspn":false,"displayname":"Anthony J. Edwards","email":"","title":"","homedirectory":"C:\\Users\\ant.edwards","logonscript":"","useraccountcontrol":66048,"samaccountname":"ant.edwards","userpassword":"","unixpassword":"","unicodepassword":"","sfupassword":"","admincount":false,"supportedencryptiontypes":[],"sidhistory":[],"allowedtodelegate":[]},"PrimaryGroupSID":"S-1-5-21-1487982659-1829050783-2281216199-513","SPNTargets":[],"UnconstrainedDelegation":false,"DomainSID":"S-1-5-21-1487982659-1829050783-2281216199","Aces":[{"PrincipalSID":"S-1-5-21-1487982659-1829050783-2281216199-512","PrincipalType":"Group","RightName":"Owns","IsInherited":false,"InheritanceHash":""},{"PrincipalSID":"S-1-5-21-1487982659-1829050783-2281216199-512","PrincipalType":"Group","RightName":"GenericAll","IsInherited":false,"InheritanceHash":""},{"PrincipalSID":"PUPPY.HTB-S-1-5-32-548","PrincipalType":"Group","RightName":"GenericAll","IsInherited":false,"InheritanceHash":""},{"PrincipalSID":"S-1-5-21-1487982659-1829050783-2281216199-526","PrincipalType":"Group","RightName":"AddKeyCredentialLink","IsInherited":true,"InheritanceHash":""},{"PrincipalSID":"S-1-5-21-1487982659-1829050783-2281216199-527","PrincipalType":"Group","RightName":"AddKeyCredentialLink","IsInherited":true,"InheritanceHash":""},{"PrincipalSID":"S-1-5-21-1487982659-1829050783-2281216199-519","PrincipalType":"Group","RightName":"GenericAll","IsInherited":true,"InheritanceHash":""},{"PrincipalSID":"PUPPY.HTB-S-1-5-32-544","PrincipalType":"Group","RightName":"GenericWrite","IsInherited":true,"InheritanceHash":""},{"PrincipalSID":"PUPPY.HTB-S-1-5-32-544","PrincipalType":"Group","RightName":"WriteOwner","IsInherited":true,"InheritanceHash":""},{"PrincipalSID":"PUPPY.HTB-S-1-5-32-544","PrincipalType":"Group","RightName":"AllExtendedRights","IsInherited":true,"InheritanceHash":""},{"PrincipalSID":"PUPPY.HTB-S-1-5-32-544","PrincipalType":"Group","RightName":"WriteDacl","IsInherited":true,"InheritanceHash":""}],"AllowedToDelegate":[],"HasSIDHistory":[],"ContainedBy":{"ObjectIdentifier":"S-1-5-21-1487982659-1829050783-2281216199","ObjectType":"Domain"}},{"ObjectIdentifier":"S-1-5-21-1487982659-1829050783-2281216199-1105","IsDeleted":false,"IsACLProtected":false,"Properties":{"domain":"PUPPY.HTB","name":"ADAM.SILVER@PUPPY.HTB","domainsid":"S-1-5-21-1487982659-1829050783-2281216199","isaclprotected":false,"distinguishedname":"CN=ADAM D. SILVER,CN=USERS,DC=PUPPY,DC=HTB","highvalue":false,"description":null,"whencreated":1739967383,"sensitive":false,"dontreqpreauth":false,"passwordnotreqd":false,"unconstraineddelegation":false,"pwdneverexpires":true,"enabled":false,"trustedtoauth":false,"lastlogon":1759760860,"lastlogontimestamp":1759655847,"pwdlastset":1759762319,"serviceprincipalnames":[],"hasspn":false,"displayname":"Adam D. Silver","email":"","title":"","homedirectory":"C:\\Users\\adam.silver","logonscript":"","useraccountcontrol":66050,"samaccountname":"adam.silver","userpassword":"","unixpassword":"","unicodepassword":"","sfupassword":"","admincount":true,"supportedencryptiontypes":[],"sidhistory":[],"allowedtodelegate":[]},"PrimaryGroupSID":"S-1-5-21-1487982659-1829050783-2281216199-513","SPNTargets":[],"UnconstrainedDelegation":false,"DomainSID":"S-1-5-21-1487982659-1829050783-2281216199","Aces":[{"PrincipalSID":"S-1-5-21-1487982659-1829050783-2281216199-512","PrincipalType":"Group","RightName":"Owns","IsInherited":false,"InheritanceHash":""},{"PrincipalSID":"S-1-5-21-1487982659-1829050783-2281216199-512","PrincipalType":"Group","RightName":"GenericWrite","IsInherited":false,"InheritanceHash":""},{"PrincipalSID":"S-1-5-21-1487982659-1829050783-2281216199-512","PrincipalType":"Group","RightName":"WriteOwner","IsInherited":false,"InheritanceHash":""},{"PrincipalSID":"S-1-5-21-1487982659-1829050783-2281216199-512","PrincipalType":"Group","RightName":"AllExtendedRights","IsInherited":false,"InheritanceHash":""},{"PrincipalSID":"S-1-5-21-1487982659-1829050783-2281216199-512","PrincipalType":"Group","RightName":"WriteDacl","IsInherited":false,"InheritanceHash":""},{"PrincipalSID":"S-1-5-21-1487982659-1829050783-2281216199-519","PrincipalType":"Group","RightName":"GenericWrite","IsInherited":false,"InheritanceHash":""},{"PrincipalSID":"S-1-5-21-1487982659-1829050783-2281216199-519","PrincipalType":"Group","RightName":"WriteOwner","IsInherited":false,"InheritanceHash":""},{"PrincipalSID":"S-1-5-21-1487982659-1829050783-2281216199-519","PrincipalType":"Group","RightName":"AllExtendedRights","IsInherited":false,"InheritanceHash":""},{"PrincipalSID":"S-1-5-21-1487982659-1829050783-2281216199-519","PrincipalType":"Group","RightName":"WriteDacl","IsInherited":false,"InheritanceHash":""},{"PrincipalSID":"S-1-5-21-1487982659-1829050783-2281216199-1109","PrincipalType":"Group","RightName":"GenericAll","IsInherited":false,"InheritanceHash":""},{"PrincipalSID":"PUPPY.HTB-S-1-5-32-544","PrincipalType":"Group","RightName":"GenericWrite","IsInherited":false,"InheritanceHash":""},{"PrincipalSID":"PUPPY.HTB-S-1-5-32-544","PrincipalType":"Group","RightName":"WriteOwner","IsInherited":false,"InheritanceHash":""},{"PrincipalSID":"PUPPY.HTB-S-1-5-32-544","PrincipalType":"Group","RightName":"AllExtendedRights","IsInherited":false,"InheritanceHash":""},{"PrincipalSID":"PUPPY.HTB-S-1-5-32-544","PrincipalType":"Group","RightName":"WriteDacl","IsInherited":false,"InheritanceHash":""}],"AllowedToDelegate":[],"HasSIDHistory":[],"ContainedBy":{"ObjectIdentifier":"3F93AA72-387D-4B17-9523-1CA9CF985828","ObjectType":"Container"}},{"ObjectIdentifier":"S-1-5-21-1487982659-1829050783-2281216199-1106","IsDeleted":false,"IsACLProtected":false,"Properties":{"domain":"PUPPY.HTB","name":"JAMIE.WILLIAMS@PUPPY.HTB","domainsid":"S-1-5-21-1487982659-1829050783-2281216199","isaclprotected":false,"distinguishedname":"CN=JAMIE S. WILLIAMS,CN=USERS,DC=PUPPY,DC=HTB","highvalue":false,"description":null,"whencreated":1739967446,"sensitive":false,"dontreqpreauth":false,"passwordnotreqd":false,"unconstraineddelegation":false,"pwdneverexpires":true,"enabled":true,"trustedtoauth":false,"lastlogon":0,"lastlogontimestamp":1741126685,"pwdlastset":1739967446,"serviceprincipalnames":[],"hasspn":false,"displayname":"Jamie S. Williams","email":"","title":"","homedirectory":"","logonscript":"","useraccountcontrol":66048,"samaccountname":"jamie.williams","userpassword":"","unixpassword":"","unicodepassword":"","sfupassword":"","admincount":false,"supportedencryptiontypes":[],"sidhistory":[],"allowedtodelegate":[]},"PrimaryGroupSID":"S-1-5-21-1487982659-1829050783-2281216199-513","SPNTargets":[],"UnconstrainedDelegation":false,"DomainSID":"S-1-5-21-1487982659-1829050783-2281216199","Aces":[{"PrincipalSID":"S-1-5-21-1487982659-1829050783-2281216199-512","PrincipalType":"Group","RightName":"Owns","IsInherited":false,"InheritanceHash":""},{"PrincipalSID":"S-1-5-21-1487982659-1829050783-2281216199-512","PrincipalType":"Group","RightName":"GenericAll","IsInherited":false,"InheritanceHash":""},{"PrincipalSID":"PUPPY.HTB-S-1-5-32-548","PrincipalType":"Group","RightName":"GenericAll","IsInherited":false,"InheritanceHash":""},{"PrincipalSID":"S-1-5-21-1487982659-1829050783-2281216199-526","PrincipalType":"Group","RightName":"AddKeyCredentialLink","IsInherited":true,"InheritanceHash":""},{"PrincipalSID":"S-1-5-21-1487982659-1829050783-2281216199-527","PrincipalType":"Group","RightName":"AddKeyCredentialLink","IsInherited":true,"InheritanceHash":""},{"PrincipalSID":"S-1-5-21-1487982659-1829050783-2281216199-519","PrincipalType":"Group","RightName":"GenericAll","IsInherited":true,"InheritanceHash":""},{"PrincipalSID":"PUPPY.HTB-S-1-5-32-544","PrincipalType":"Group","RightName":"GenericWrite","IsInherited":true,"InheritanceHash":""},{"PrincipalSID":"PUPPY.HTB-S-1-5-32-544","PrincipalType":"Group","RightName":"WriteOwner","IsInherited":true,"InheritanceHash":""},{"PrincipalSID":"PUPPY.HTB-S-1-5-32-544","PrincipalType":"Group","RightName":"AllExtendedRights","IsInherited":true,"InheritanceHash":""},{"PrincipalSID":"PUPPY.HTB-S-1-5-32-544","PrincipalType":"Group","RightName":"WriteDacl","IsInherited":true,"InheritanceHash":""}],"AllowedToDelegate":[],"HasSIDHistory":[],"ContainedBy":{"ObjectIdentifier":"3F93AA72-387D-4B17-9523-1CA9CF985828","ObjectType":"Container"}},{"ObjectIdentifier":"S-1-5-21-1487982659-1829050783-2281216199-1107","IsDeleted":false,"IsACLProtected":false,"Properties":{"domain":"PUPPY.HTB","name":"STEPH.COOPER@PUPPY.HTB","domainsid":"S-1-5-21-1487982659-1829050783-2281216199","isaclprotected":false,"distinguishedname":"CN=STEPHEN W. COOPER,OU=PUPPY ADMINS,DC=PUPPY,DC=HTB","highvalue":false,"description":null,"whencreated":1739967660,"sensitive":false,"dontreqpreauth":false,"passwordnotreqd":false,"unconstraineddelegation":false,"pwdneverexpires":true,"enabled":true,"trustedtoauth":false,"lastlogon":1759656520,"lastlogontimestamp":1759656520,"pwdlastset":1739967660,"serviceprincipalnames":[],"hasspn":false,"displayname":"Stephen W. Cooper","email":"","title":"","homedirectory":"C:\\Users\\Steph.cooper","logonscript":"","useraccountcontrol":66048,"samaccountname":"steph.cooper","userpassword":"","unixpassword":"","unicodepassword":"","sfupassword":"","admincount":false,"supportedencryptiontypes":["Not defined"],"sidhistory":[],"allowedtodelegate":[]},"PrimaryGroupSID":"S-1-5-21-1487982659-1829050783-2281216199-513","SPNTargets":[],"UnconstrainedDelegation":false,"DomainSID":"S-1-5-21-1487982659-1829050783-2281216199","Aces":[{"PrincipalSID":"S-1-5-21-1487982659-1829050783-2281216199-512","PrincipalType":"Group","RightName":"Owns","IsInherited":false,"InheritanceHash":""},{"PrincipalSID":"S-1-5-21-1487982659-1829050783-2281216199-512","PrincipalType":"Group","RightName":"GenericAll","IsInherited":false,"InheritanceHash":""},{"PrincipalSID":"PUPPY.HTB-S-1-5-32-548","PrincipalType":"Group","RightName":"GenericAll","IsInherited":false,"InheritanceHash":""},{"PrincipalSID":"S-1-5-21-1487982659-1829050783-2281216199-526","PrincipalType":"Group","RightName":"AddKeyCredentialLink","IsInherited":true,"InheritanceHash":""},{"PrincipalSID":"S-1-5-21-1487982659-1829050783-2281216199-527","PrincipalType":"Group","RightName":"AddKeyCredentialLink","IsInherited":true,"InheritanceHash":""},{"PrincipalSID":"S-1-5-21-1487982659-1829050783-2281216199-519","PrincipalType":"Group","RightName":"GenericAll","IsInherited":true,"InheritanceHash":""},{"PrincipalSID":"PUPPY.HTB-S-1-5-32-544","PrincipalType":"Group","RightName":"GenericWrite","IsInherited":true,"InheritanceHash":""},{"PrincipalSID":"PUPPY.HTB-S-1-5-32-544","PrincipalType":"Group","RightName":"WriteOwner","IsInherited":true,"InheritanceHash":""},{"PrincipalSID":"PUPPY.HTB-S-1-5-32-544","PrincipalType":"Group","RightName":"AllExtendedRights","IsInherited":true,"InheritanceHash":""},{"PrincipalSID":"PUPPY.HTB-S-1-5-32-544","PrincipalType":"Group","RightName":"WriteDacl","IsInherited":true,"InheritanceHash":""}],"AllowedToDelegate":[],"HasSIDHistory":[],"ContainedBy":{"ObjectIdentifier":"497630F9-2C84-4BDA-8FD4-4812BC896B99","ObjectType":"OU"}},{"ObjectIdentifier":"S-1-5-21-1487982659-1829050783-2281216199-1111","IsDeleted":false,"IsACLProtected":false,"Properties":{"domain":"PUPPY.HTB","name":"STEPH.COOPER_ADM@PUPPY.HTB","domainsid":"S-1-5-21-1487982659-1829050783-2281216199","isaclprotected":false,"distinguishedname":"CN=STEPHEN A. COOPER_ADM,OU=PUPPY ADMINS,DC=PUPPY,DC=HTB","highvalue":false,"description":null,"whencreated":1741449040,"sensitive":false,"dontreqpreauth":false,"passwordnotreqd":false,"unconstraineddelegation":false,"pwdneverexpires":true,"enabled":true,"trustedtoauth":false,"lastlogon":0,"lastlogontimestamp":1759658834,"pwdlastset":1741449040,"serviceprincipalnames":[],"hasspn":false,"displayname":"Stephen A. Cooper","email":"","title":"","homedirectory":"","logonscript":"","useraccountcontrol":66048,"samaccountname":"steph.cooper_adm","userpassword":"","unixpassword":"","unicodepassword":"","sfupassword":"","admincount":true,"supportedencryptiontypes":[],"sidhistory":[],"allowedtodelegate":[]},"PrimaryGroupSID":"S-1-5-21-1487982659-1829050783-2281216199-513","SPNTargets":[],"UnconstrainedDelegation":false,"DomainSID":"S-1-5-21-1487982659-1829050783-2281216199","Aces":[{"PrincipalSID":"S-1-5-21-1487982659-1829050783-2281216199-512","PrincipalType":"Group","RightName":"Owns","IsInherited":false,"InheritanceHash":""},{"PrincipalSID":"S-1-5-21-1487982659-1829050783-2281216199-512","PrincipalType":"Group","RightName":"GenericWrite","IsInherited":false,"InheritanceHash":""},{"PrincipalSID":"S-1-5-21-1487982659-1829050783-2281216199-512","PrincipalType":"Group","RightName":"WriteOwner","IsInherited":false,"InheritanceHash":""},{"PrincipalSID":"S-1-5-21-1487982659-1829050783-2281216199-512","PrincipalType":"Group","RightName":"AllExtendedRights","IsInherited":false,"InheritanceHash":""},{"PrincipalSID":"S-1-5-21-1487982659-1829050783-2281216199-512","PrincipalType":"Group","RightName":"WriteDacl","IsInherited":false,"InheritanceHash":""},{"PrincipalSID":"S-1-5-21-1487982659-1829050783-2281216199-519","PrincipalType":"Group","RightName":"GenericWrite","IsInherited":false,"InheritanceHash":""},{"PrincipalSID":"S-1-5-21-1487982659-1829050783-2281216199-519","PrincipalType":"Group","RightName":"WriteOwner","IsInherited":false,"InheritanceHash":""},{"PrincipalSID":"S-1-5-21-1487982659-1829050783-2281216199-519","PrincipalType":"Group","RightName":"AllExtendedRights","IsInherited":false,"InheritanceHash":""},{"PrincipalSID":"S-1-5-21-1487982659-1829050783-2281216199-519","PrincipalType":"Group","RightName":"WriteDacl","IsInherited":false,"InheritanceHash":""},{"PrincipalSID":"PUPPY.HTB-S-1-5-32-544","PrincipalType":"Group","RightName":"GenericWrite","IsInherited":false,"InheritanceHash":""},{"PrincipalSID":"PUPPY.HTB-S-1-5-32-544","PrincipalType":"Group","RightName":"WriteOwner","IsInherited":false,"InheritanceHash":""},{"PrincipalSID":"PUPPY.HTB-S-1-5-32-544","PrincipalType":"Group","RightName":"AllExtendedRights","IsInherited":false,"InheritanceHash":""},{"PrincipalSID":"PUPPY.HTB-S-1-5-32-544","PrincipalType":"Group","RightName":"WriteDacl","IsInherited":false,"InheritanceHash":""}],"AllowedToDelegate":[],"HasSIDHistory":[],"ContainedBy":{"ObjectIdentifier":"497630F9-2C84-4BDA-8FD4-4812BC896B99","ObjectType":"OU"}},{"ObjectIdentifier":"PUPPY.HTB-S-1-5-20","IsDeleted":false,"IsACLProtected":false,"Properties":{"domain":"","name":"NT AUTHORITY@PUPPY.HTB","domainsid":"S-1-5-21-1487982659-1829050783-2281216199","isaclprotected":false,"distinguishedname":"","highvalue":false,"description":null,"whencreated":0,"sensitive":false,"dontreqpreauth":false,"passwordnotreqd":false,"unconstraineddelegation":false,"pwdneverexpires":false,"enabled":false,"trustedtoauth":false,"lastlogon":0,"lastlogontimestamp":0,"pwdlastset":0,"serviceprincipalnames":[],"hasspn":false,"displayname":"","email":"","title":"","homedirectory":"","logonscript":"","useraccountcontrol":0,"samaccountname":"","userpassword":"","unixpassword":"","unicodepassword":"","sfupassword":"","admincount":false,"supportedencryptiontypes":[],"sidhistory":[],"allowedtodelegate":[]},"PrimaryGroupSID":"","SPNTargets":[],"UnconstrainedDelegation":false,"DomainSID":"","Aces":[],"AllowedToDelegate":[],"HasSIDHistory":[],"ContainedBy":{"ObjectIdentifier":"00F21626-5184-4C04-8538-3D6DB0420964","ObjectType":"Container"}}],"meta":{"methods":0,"type":"users","count":10,"version":6,"collectorversion":"RustHound-CE v2.4.0"}}